distpy/README.md
distpy/__init__.py
distpy/__pycache__/__init__.cpython-38.pyc
distpy/calc/__init__.py
distpy/calc/agnostic.py
distpy/calc/cupy_facade.py
distpy/calc/extra_numpy.py
distpy/calc/extra_pyplot.py
distpy/calc/plt_command_set.py
distpy/calc/processing_commands.py
distpy/calc/pub_command_set.py
distpy/calc/unit_handler.py
distpy/controllers/__init__.py
distpy/controllers/edge_processing.py
distpy/controllers/parallel_plots.py
distpy/controllers/parallel_strainrate_processing.py
distpy/ingesters/__init__.py
distpy/ingesters/parallel_convert_las2fbe.py
distpy/ingesters/parallel_ingest.py
distpy/ingesters/parallel_ingest_csv.py
distpy/ingesters/parallel_ingest_h5.py
distpy/ingesters/parallel_ingest_sgy.py
distpy/ingesters/parallel_ingest_witsml.py
distpy/io_help/__init__.py
distpy/io_help/directory_services.py
distpy/io_help/dirswap.py
distpy/io_help/h5_helpers.py
distpy/io_help/io_helpers.py
distpy/io_help/sgy.py
distpy/io_help/timeshift.py
distpy/io_help/witsmlfbe.py
distpy/workers/__init__.py
distpy/workers/plotgenerator.py
distpy/workers/strainrate2summary.py
distpy-1.32.3.dist-info/LICENSE
distpy-1.32.3.dist-info/METADATA
distpy-1.32.3.dist-info/WHEEL
distpy-1.32.3.dist-info/top_level.txt
distpy-1.32.3.dist-info/RECORD
